clickhouse_repl/__init__.py
clickhouse_repl/main.py
clickhouse_repl-1.0.0.dist-info/entry_points.txt
clickhouse_repl-1.0.0.dist-info/LICENSE
clickhouse_repl-1.0.0.dist-info/WHEEL
clickhouse_repl-1.0.0.dist-info/METADATA
clickhouse_repl-1.0.0.dist-info/RECORD
