Metadata-Version: 2.1
Name: clickhouse-repl
Version: 1.0.0
Summary: A toolkit for running ClickHouse queries interactively, leveraging the perks of an ipython console
License: MIT
Author: klic.tools
Requires-Python: >=3.7,<4.0
Classifier: License :: OSI Approved :: MIT License
Classifier: Programming Language :: Python :: 3
Classifier: Programming Language :: Python :: 3.7
Classifier: Programming Language :: Python :: 3.8
Classifier: Programming Language :: Python :: 3.9
Requires-Dist: click (>=7.1.2,<8.0.0)
Requires-Dist: clickhouse-driver (>=0.2.0,<0.3.0)
Requires-Dist: ipython (>=7.9.0,<8.0.0)
Requires-Dist: jedi (<0.18.0)
